pg_spot_operator/__init__.py
pg_spot_operator/__main__.py
pg_spot_operator/base.py
pg_spot_operator/cli.py
pg_spot_operator/cloud_api.py
pg_spot_operator/cmdb.py
pg_spot_operator/constants.py
pg_spot_operator/instance_type_selection.py
pg_spot_operator/manifests.py
pg_spot_operator/operator.py
pg_spot_operator/pgtuner.py
pg_spot_operator/util.py
pg_spot_operator/cloud_impl/__init__.py
pg_spot_operator/cloud_impl/aws_cache.py
pg_spot_operator/cloud_impl/aws_client.py
pg_spot_operator/cloud_impl/aws_s3.py
pg_spot_operator/cloud_impl/aws_spot.py
pg_spot_operator/cloud_impl/aws_vm.py
pg_spot_operator/cloud_impl/cloud_structs.py
pg_spot_operator/cloud_impl/cloud_util.py
pg_spot_operator/cmdb_impl/__init__.py
pg_spot_operator/cmdb_impl/schema_manager.py
pg_spot_operator/cmdb_impl/sqlite.py
pg_spot_operator/cmdb_impl/sqlite_migrations.py
pg_spot_operator-0.9.60.dist-info/licenses/LICENSE
pg_spot_operator-0.9.60.dist-info/METADATA
pg_spot_operator-0.9.60.dist-info/WHEEL
pg_spot_operator-0.9.60.dist-info/entry_points.txt
pg_spot_operator-0.9.60.dist-info/top_level.txt
pg_spot_operator-0.9.60.dist-info/RECORD
