Metadata-Version: 2.4
Name: pg_spot_operator
Version: 0.9.60
Summary: Maintains stateful Postgres on Spot VMs
Home-page: https://github.com/pg-spot-ops/pg-spot-operator/
Author: pg-spot-ops
License-File: LICENSE
Requires-Dist: typed-argument-parser
Requires-Dist: boto3
Requires-Dist: botocore
Requires-Dist: requests
Requires-Dist: deepdiff
Requires-Dist: python-dateutil
Requires-Dist: types-python-dateutil
Requires-Dist: pydantic
Requires-Dist: pyyaml
Requires-Dist: types-PyYAML
Requires-Dist: sqlalchemy
Requires-Dist: unidecode
Requires-Dist: prettytable
Requires-Dist: humanize
Provides-Extra: test
Requires-Dist: pytest; extra == "test"
Requires-Dist: coverage; extra == "test"
Requires-Dist: flake8; extra == "test"
Requires-Dist: black; extra == "test"
Requires-Dist: isort; extra == "test"
Requires-Dist: pytest-cov; extra == "test"
Requires-Dist: mypy; extra == "test"
Requires-Dist: gitchangelog; extra == "test"
Requires-Dist: mkdocs; extra == "test"
Requires-Dist: typed-argument-parser; extra == "test"
Requires-Dist: boto3; extra == "test"
Requires-Dist: botocore; extra == "test"
Requires-Dist: requests; extra == "test"
Requires-Dist: types-requests; extra == "test"
Requires-Dist: deepdiff; extra == "test"
Requires-Dist: python-dateutil; extra == "test"
Requires-Dist: types-python-dateutil; extra == "test"
Requires-Dist: pydantic; extra == "test"
Requires-Dist: pyyaml; extra == "test"
Requires-Dist: types-PyYAML; extra == "test"
Requires-Dist: sqlalchemy; extra == "test"
Requires-Dist: unidecode; extra == "test"
Requires-Dist: prettytable; extra == "test"
Requires-Dist: humanize; extra == "test"
Dynamic: author
Dynamic: description
Dynamic: description-content-type
Dynamic: home-page
Dynamic: license-file
Dynamic: provides-extra
Dynamic: requires-dist
Dynamic: summary
